{
  "topic": "Uso del gerundio",
  "exampleQuestion": "1. Es el inciso que tiene la oración en donde está incorrectamente utilizada la palabra subrayada.",
  "exampleOptions": [
    "a) <u>Andando</u> por las oscuras calles, el peligro lo acechaba en cada esquina.",
    "b) En <u>llegando</u> tú, me iré yo.",
    "c) Llegaron a su casa, <u>teniendo</u> que regresarse porque estaba cerrada.",
    "d) Las damas, <u>cubriendo</u> sus cabellos con un tenue velo, entraron rápidamente a la iglesia."
  ],
  "answer": 2,
  "imageURL": ""
}
